IF_SPI/spi_master.v
module spi_master #(
    parameter CPOL = 0,
    parameter CPHA = 0
)
(
    input clk           ,
    input rstn          ,

    output SCLK         ,
    input MISO          ,
    output MOSI         ,
    output [1:0] CS     ,

    input [7:0] tx_data ,
    input tx_en         ,

    output  spi_busy

);

reg clk_en1, clk_en2            ;
reg [9:0] clk_cnt = 10'd0       ;

reg spi_clk;


parameter [9:0] CLK_DIV = 10'd500;//分频 假设（50Mhz/100K/ - 1'b1=499

always@(posedge clk or negedge rstn) begin
    if(~rstn)
        clk_en1 <= 1'b0;
    else if(clk_cnt == CLK_DIV-1)
        clk_en1 <= 1'b1;
    else
        clk_en1 <= 1'b0;
end

always@(posedge clk or negedge rstn) begin
    if(~rstn)
        clk_en2 <= 1'b0;
    else if(clk_cnt == CLK_DIV/2-1)
        clk_en2 <= 1'b1;
    else
        clk_en2 <= 1'b0;
end

always@(posedge clk or negedge rstn) begin
    if(~rstn || clk_cnt == CLK_DIV)
        clk_cnt <= 'd0;
    else
        clk_cnt <= clk_cnt + 1'b1;
end

always@(posedge clk or negedge rstn) begin
    if(~rstn || tx_en)
        spi_clk <= 1'b0;
    else if(clk_en2)            // clk_en2: n
        spi_clk <= 1'b0;
    else if(clk_en1)            // clk_en1: p
        spi_clk <= 1'b1;          
    else
        spi_clk <= spi_clk;
end

reg spi_clk_d;
wire spi_done, spi_load;
reg [7:0] spi_data_reg;
reg [3:0] tx_cnt;
reg [1:0] state, next_state;

parameter IDLE  = 2'b00     ;
parameter START = 2'b01     ;
parameter TRANS = 2'b11     ;
parameter DONE  = 2'b10     ;


assign SCLK = (state == TRANS)? (CPOL? ~spi_clk : spi_clk):1'b0;
assign MOSI = (state == TRANS)? spi_data_reg[7]:1'b0;

assign spi_load = CPHA ? clk_en1 : clk_en2;     // load time control

assign spi_busy = (state == TRANS) ? 1'b1 : 1'b0;
assign CS = 2'b00;
assign spi_done = (state == DONE) ? 1'b1 : 1'b0;

always @(posedge clk or negedge rstn) begin
    if(~rstn)
        spi_clk_d <= 1'b1;
    else
        spi_clk_d <= spi_clk;
end

always @(posedge clk or negedge rstn) begin
    if(~rstn)
        state <= IDLE;
    else
        state <= next_state;
end

always @(*) begin
    next_state = IDLE;
    case (state)
        IDLE: begin
            if(tx_en)
                if(~CPHA)
                    next_state = START;
                else
                    next_state = TRANS;
            else
                next_state = IDLE;
        end

        START: begin
            if(spi_load)
                next_state = TRANS;
            else
                next_state = START;
        end

        TRANS: begin
            if(tx_cnt == 'd8 && spi_load)
                next_state = DONE;
            else
                next_state = TRANS;
        end

        DONE: begin
            if(spi_load)
                next_state = IDLE;
            else
                next_state = DONE;
        end

        default: begin
            next_state = IDLE;
        end
            
    endcase
end



/* 待传输数据的寄存器 */
always @(posedge clk or negedge rstn) begin
    if(~rstn || spi_done)
        spi_data_reg <= 'd0;
    else if(tx_en)
        spi_data_reg <= tx_data;
    else if(state == TRANS && spi_load)
        spi_data_reg[7:0] <= {spi_data_reg[6:0],1'b0};
    else
        spi_data_reg <= spi_data_reg;
end


always @(posedge spi_clk_d or negedge rstn) begin
    if(~rstn || tx_cnt == 'd8)
        tx_cnt <= 'd0;
    else if(state == TRANS)
        tx_cnt <= tx_cnt + 1'b1;
    else
        tx_cnt <= tx_cnt;
end



endmodule

IF_SPI/spi_master_tb.v
module spi_master_tb;


    reg clk = 1'b0;
    reg rstn = 1'b1;

    reg [7:0] tx_data = 'd0;
    reg tx_en;
    
    wire spi_mosi;
    wire spi_miso;
    wire spi_clk;
    wire spi_cs;
    wire spi_busy;

    initial begin
        clk = 1'b0;
        rstn = 1'b0;
        #100;
        rstn = 1'b1;
    end
    always begin
        #10 clk = ~clk;
    end

    initial
        tx_en = 1'b0;

    initial begin
        #10000;
        spi_trans(1);
        #200_000;
        spi_trans('b1000_0001);

    end

initial begin
    $dumpfile("spi_master_sim.vcd");
    $dumpvars;
    #1000_000 $finish;
end


    spi_master #(
                   .CPOL(0),
                   .CPHA(1)
               ) u_spi
               (
                   .clk            (clk            ),
                   .rstn           (rstn           ),
                   .SCLK           (spi_clk        ),
                   .MISO           (spi_miso       ),
                   .MOSI           (spi_mosi       ),
                   .CS             (spi_cs         ),
                   .tx_data        (tx_data        ),
                   .tx_en          (tx_en          ),
                   .spi_busy       (spi_busy       )

               );


task spi_trans;
    input [7:0] data;
    begin
        tx_en = 1'b1;
        tx_data = data;
        # 20
        tx_en = 1'b0;
    end
endtask //automatic



endmodule

IF_SPI/spi_master_sim.vcd
$date
	Fri Feb 24 10:59:59 2023
$end
$version
	ModelSim Version 10.6d
$end
$timescale
	1ns
$end

$scope module spi_master_tb $end
$var reg 1 ! clk $end
$var reg 1 " rstn $end
$var reg 8 # tx_data [7:0] $end
$var reg 1 $ tx_en $end
$var wire 1 % spi_mosi $end
$var wire 1 & spi_miso $end
$var wire 1 ' spi_clk $end
$var wire 1 ( spi_cs $end
$var wire 1 ) spi_busy $end

$scope task spi_trans $end
$var reg 8 * data [7:0] $end
$upscope $end

$scope module u_spi $end
$var parameter 32 + CPOL $end
$var parameter 32 , CPHA $end
$var parameter 10 - CLK_DIV $end
$var parameter 2 . IDLE $end
$var parameter 2 / START $end
$var parameter 2 0 TRANS $end
$var parameter 2 1 DONE $end
$var wire 1 2 clk $end
$var wire 1 3 rstn $end
$var wire 1 ' SCLK $end
$var wire 1 & MISO $end
$var wire 1 % MOSI $end
$var wire 1 4 CS [1] $end
$var wire 1 ( CS [0] $end
$var wire 1 5 tx_data [7] $end
$var wire 1 6 tx_data [6] $end
$var wire 1 7 tx_data [5] $end
$var wire 1 8 tx_data [4] $end
$var wire 1 9 tx_data [3] $end
$var wire 1 : tx_data [2] $end
$var wire 1 ; tx_data [1] $end
$var wire 1 < tx_data [0] $end
$var wire 1 = tx_en $end
$var wire 1 ) spi_busy $end
$var reg 1 > clk_en1 $end
$var reg 1 ? clk_en2 $end
$var reg 10 @ clk_cnt [9:0] $end
$var reg 1 A spi_clk $end
$var reg 1 B spi_clk_d $end
$var wire 1 C spi_done $end
$var wire 1 D spi_load $end
$var reg 8 E spi_data_reg [7:0] $end
$var reg 4 F tx_cnt [3:0] $end
$var reg 2 G state [1:0] $end
$var reg 2 H next_state [1:0] $end
$upscope $end
$upscope $end
$enddefinitions $end
#0
$dumpvars
0!
0"
b0 #
0$
0>
0?
b0 @
0A
1B
b0 E
b0 F
b0 G
b0 H
bx *
b0 +
b1 ,
b111110100 -
b0 .
b1 /
b11 0
b10 1
0%
z&
0'
0(
0)
0C
0D
0=
0<
0;
0:
09
08
07
06
05
03
02
04
$end
#10
1!
12
#20
0!
02
#30
1!
12
#40
0!
02
#50
1!
12
#60
0!
02
#70
1!
12
#80
0!
02
#90
1!
12
#100
1"
0!
13
02
#110
1!
12
0B
b1 @
#120
0!
02
#130
1!
12
b10 @
#140
0!
02
#150
1!
12
b11 @
#160
0!
02
#170
1!
12
b100 @
#180
0!
02
#190
1!
12
b101 @
#200
0!
02
#210
1!
12
b110 @
#220
0!
02
#230
1!
12
b111 @
#240
0!
02
#250
1!
12
b1000 @
#260
0!
02
#270
1!
12
b1001 @
#280
0!
02
#290
1!
12
b1010 @
#300
0!
02
#310
1!
12
b1011 @
#320
0!
02
#330
1!
12
b1100 @
#340
0!
02
#350
1!
12
b1101 @
#360
0!
02
#370
1!
12
b1110 @
#380
0!
02
#390
1!
12
b1111 @
#400
0!
02
#410
1!
12
b10000 @
#420
0!
02
#430
1!
12
b10001 @
#440
0!
02
#450
1!
12
b10010 @
#460
0!
02
#470
1!
12
b10011 @
#480
0!
02
#490
1!
12
b10100 @
#500
0!
02
#510
1!
12
b10101 @
#520
0!
02
#530
1!
12
b10110 @
#540
0!
02
#550
1!
12
b10111 @
#560
0!
02
#570
1!
12
b11000 @
#580
0!
02
#590
1!
12
b11001 @
#600
0!
02
#610
1!
12
b11010 @
#620
0!
02
#630
1!
12
b11011 @
#640
0!
02
#650
1!
12
b11100 @
#660
0!
02
#670
1!
12
b11101 @
#680
0!
02
#690
1!
12
b11110 @
#700
0!
02
#710
1!
12
b11111 @
#720
0!
02
#730
1!
12
b100000 @
#740
0!
02
#750
1!
12
b100001 @
#760
0!
02
#770
1!
12
b100010 @
#780
0!
02
#790
1!
12
b100011 @
#800
0!
02
#810
1!
12
b100100 @
#820
0!
02
#830
1!
12
b100101 @
#840
0!
02
#850
1!
12
b100110 @
#860
0!
02
#870
1!
12
b100111 @
#880
0!
02
#890
1!
12
b101000 @
#900
0!
02
#910
1!
12
b101001 @
#920
0!
02
#930
1!
12
b101010 @
#940
0!
02
#950
1!
12
b101011 @
#960
0!
02
#970
1!
12
b101100 @
#980
0!
02
#990
1!
12
b101101 @
#1000
0!
02
#1010
1!
12
b101110 @
#1020
0!
02
#1030
1!
12
b101111 @
#1040
0!
02
#1050
1!
12
b110000 @
#1060
0!
02
#1070
1!
12
b110001 @
#1080
0!
02
#1090
1!
12
b110010 @
#1100
0!
02
#1110
1!
12
b110011 @
#1120
0!
02
#1130
1!
12
b110100 @
#1140
0!
02
#1150
1!
12
b110101 @
#1160
0!
02
#1170
1!
12
b110110 @
#1180
0!
02
#1190
1!
12
b110111 @
#1200
0!
02
#1210
1!
12
b111000 @
#1220
0!
02
#1230
1!
12
b111001 @
#1240
0!
02
#1250
1!
12
b111010 @
#1260
0!
02
#1270
1!
12
b111011 @
#1280
0!
02
#1290
1!
12
b111100 @
#1300
0!
02
#1310
1!
12
b111101 @
#1320
0!
02
#1330
1!
12
b111110 @
#1340
0!
02
#1350
1!
12
b111111 @
#1360
0!
02
#1370
1!
12
b1000000 @
#1380
0!
02
#1390
1!
12
b1000001 @
#1400
0!
02
#1410
1!
12
b1000010 @
#1420
0!
02
#1430
1!
12
b1000011 @
#1440
0!
02
#1450
1!
12
b1000100 @
#1460
0!
02
#1470
1!
12
b1000101 @
#1480
0!
02
#1490
1!
12
b1000110 @
#1500
0!
02
#1510
1!
12
b1000111 @
#1520
0!
02
#1530
1!
12
b1001000 @
#1540
0!
02
#1550
1!
12
b1001001 @
#1560
0!
02
#1570
1!
12
b1001010 @
#1580
0!
02
#1590
1!
12
b1001011 @
#1600
0!
02
#1610
1!
12
b1001100 @
#1620
0!
02
#1630
1!
12
b1001101 @
#1640
0!
02
#1650
1!
12
b1001110 @
#1660
0!
02
#1670
1!
12
b1001111 @
#1680
0!
02
#1690
1!
12
b1010000 @
#1700
0!
02
#1710
1!
12
b1010001 @
#1720
0!
02
#1730
1!
12
b1010010 @
#1740
0!
02
#1750
1!
12
b1010011 @
#1760
0!
02
#1770
1!
12
b1010100 @
#1780
0!
02
#1790
1!
12
b1010101 @
#1800
0!
02
#1810
1!
12
b1010110 @
#1820
0!
02
#1830
1!
12
b1010111 @
#1840
0!
02
#1850
1!
12
b1011000 @
#1860
0!
02
#1870
1!
12
b1011001 @
#1880
0!
02
#1890
1!
12
b1011010 @
#1900
0!
02
#1910
1!
12
b1011011 @
#1920
0!
02
#1930
1!
12
b1011100 @
#1940
0!
02
#1950
1!
12
b1011101 @
#1960
0!
02
#1970
1!
12
b1011110 @
#1980
0!
02
#1990
1!
12
b1011111 @
#2000
0!
02
#2010
1!
12
b1100000 @
#2020
0!
02
#2030
1!
12
b1100001 @
#2040
0!
02
#2050
1!
12
b1100010 @
#2060
0!
02
#2070
1!
12
b1100011 @
#2080
0!
02
#2090
1!
12
b1100100 @
#2100
0!
02
#2110
1!
12
b1100101 @
#2120
0!
02
#2130
1!
12
b1100110 @
#2140
0!
02
#2150
1!
12
b1100111 @
#2160
0!
02
#2170
1!
12
b1101000 @
#2180
0!
02
#2190
1!
12
b1101001 @
#2200
0!
02
#2210
1!
12
b1101010 @
#2220
0!
02
#2230
1!
12
b1101011 @
#2240
0!
02
#2250
1!
12
b1101100 @
#2260
0!
02
#2270
1!
12
b1101101 @
#2280
0!
02
#2290
1!
12
b1101110 @
#2300
0!
02
#2310
1!
12
b1101111 @
#2320
0!
02
#2330
1!
12
b1110000 @
#2340
0!
02
#2350
1!
12
b1110001 @
#2360
0!
02
#2370
1!
12
b1110010 @
#2380
0!
02
#2390
1!
12
b1110011 @
#2400
0!
02
#2410
1!
12
b1110100 @
#2420
0!
02
#2430
1!
12
b1110101 @
#2440
0!
02
#2450
1!
12
b1110110 @
#2460
0!
02
#2470
1!
12
b1110111 @
#2480
0!
02
#2490
1!
12
b1111000 @
#2500
0!
02
#2510
1!
12
b1111001 @
#2520
0!
02
#2530
1!
12
b1111010 @
#2540
0!
02
#2550
1!
12
b1111011 @
#2560
0!
02
#2570
1!
12
b1111100 @
#2580
0!
02
#2590
1!
12
b1111101 @
#2600
0!
02
#2610
1!
12
b1111110 @
#2620
0!
02
#2630
1!
12
b1111111 @
#2640
0!
02
#2650
1!
12
b10000000 @
#2660
0!
02
#2670
1!
12
b10000001 @
#2680
0!
02
#2690
1!
12
b10000010 @
#2700
0!
02
#2710
1!
12
b10000011 @
#2720
0!
02
#2730
1!
12
b10000100 @
#2740
0!
02
#2750
1!
12
b10000101 @
#2760
0!
02
#2770
1!
12
b10000110 @
#2780
0!
02
#2790
1!
12
b10000111 @
#2800
0!
02
#2810
1!
12
b10001000 @
#2820
0!
02
#2830
1!
12
b10001001 @
#2840
0!
02
#2850
1!
12
b10001010 @
#2860
0!
02
#2870
1!
12
b10001011 @
#2880
0!
02
#2890
1!
12
b10001100 @
#2900
0!
02
#2910
1!
12
b10001101 @
#2920
0!
02
#2930
1!
12
b10001110 @
#2940
0!
02
#2950
1!
12
b10001111 @
#2960
0!
02
#2970
1!
12
b10010000 @
#2980
0!
02
#2990
1!
12
b10010001 @
#3000
0!
02
#3010
1!
12
b10010010 @
#3020
0!
02
#3030
1!
12
b10010011 @
#3040
0!
02
#3050
1!
12
b10010100 @
#3060
0!
02
#3070
1!
12
b10010101 @
#3080
0!
02
#3090
1!
12
b10010110 @
#3100
0!
02
#3110
1!
12
b10010111 @
#3120
0!
02
#3130
1!
12
b10011000 @
#3140
0!
02
#3150
1!
12
b10011001 @
#3160
0!
02
#3170
1!
12
b10011010 @
#3180
0!
02
#3190
1!
12
b10011011 @
#3200
0!
02
#3210
1!
12
b10011100 @
#3220
0!
02
#3230
1!
12
b10011101 @
#3240
0!
02
#3250
1!
12
b10011110 @
#3260
0!
02
#3270
1!
12
b10011111 @
#3280
0!
02
#3290
1!
12
b10100000 @
#3300
0!
02
#3310
1!
12
b10100001 @
#3320
0!
02
#3330
1!
12
b10100010 @
#3340
0!
02
#3350
1!
12
b10100011 @
#3360
0!
02
#3370
1!
12
b10100100 @
#3380
0!
02
#3390
1!
12
b10100101 @
#3400
0!
02
#3410
1!
12
b10100110 @
#3420
0!
02
#3430
1!
12
b10100111 @
#3440
0!
02
#3450
1!
12
b10101000 @
#3460
0!
02
#3470
1!
12
b10101001 @
#3480
0!
02
#3490
1!
12
b10101010 @
#3500
0!
02
#3510
1!
12
b10101011 @
#3520
0!
02
#3530
1!
12
b10101100 @
#3540
0!
02
#3550
1!
12
b10101101 @
#3560
0!
02
#3570
1!
12
b10101110 @
#3580
0!
02
#3590
1!
12
b10101111 @
#3600
0!
02
#3610
1!
12
b10110000 @
#3620
0!
02
#3630
1!
12
b10110001 @
#3640
0!
02
#3650
1!
12
b10110010 @
#3660
0!
02
#3670
1!
12
b10110011 @
#3680
0!
02
#3690
1!
12
b10110100 @
#3700
0!
02
#3710
1!
12
b10110101 @
#3720
0!
02
#3730
1!
12
b10110110 @
#3740
0!
02
#3750
1!
12
b10110111 @
#3760
0!
02
#3770
1!
12
b10111000 @
#3780
0!
02
#3790
1!
12
b10111001 @
#3800
0!
02
#3810
1!
12
b10111010 @
#3820
0!
02
#3830
1!
12
b10111011 @
#3840
0!
02
#3850
1!
12
b10111100 @
#3860
0!
02
#3870
1!
12
b10111101 @
#3880
0!
02
#3890
1!
12
b10111110 @
#3900
0!
02
#3910
1!
12
b10111111 @
#3920
0!
02
#3930
1!
12
b11000000 @
#3940
0!
02
#3950
1!
12
b11000001 @
#3960
0!
02
#3970
1!
12
b11000010 @
#3980
0!
02
#3990
1!
12
b11000011 @
#4000
0!
02
#4010
1!
12
b11000100 @
#4020
0!
02
#4030
1!
12
b11000101 @
#4040
0!
02
#4050
1!
12
b11000110 @
#4060
0!
02
#4070
1!
12
b11000111 @
#4080
0!
02
#4090
1!
12
b11001000 @
#4100
0!
02
#4110
1!
12
b11001001 @
#4120
0!
02
#4130
1!
12
b11001010 @
#4140
0!
02
#4150
1!
12
b11001011 @
#4160
0!
02
#4170
1!
12
b11001100 @
#4180
0!
02
#4190
1!
12
b11001101 @
#4200
0!
02
#4210
1!
12
b11001110 @
#4220
0!
02
#4230
1!
12
b11001111 @
#4240
0!
02
#4250
1!
12
b11010000 @
#4260
0!
02
#4270
1!
12
b11010001 @
#4280
0!
02
#4290
1!
12
b11010010 @
#4300
0!
02
#4310
1!
12
b11010011 @
#4320
0!
02
#4330
1!
12
b11010100 @
#4340
0!
02
#4350
1!
12
b11010101 @
#4360
0!
02
#4370
1!
12
b11010110 @
#4380
0!
02
#4390
1!
12
b11010111 @
#4400
0!
02
#4410
1!
12
b11011000 @
#4420
0!
02
#4430
1!
12
b11011001 @
#4440
0!
02
#4450
1!
12
b11011010 @
#4460
0!
02
#4470
1!
12
b11011011 @
#4480
0!
02
#4490
1!
12
b11011100 @
#4500
0!
02
#4510
1!
12
b11011101 @
#4520
0!
02
#4530
1!
12
b11011110 @
#4540
0!
02
#4550
1!
12
b11011111 @
#4560
0!
02
#4570
1!
12
b11100000 @
#4580
0!
02
#4590
1!
12
b11100001 @
#4600
0!
02
#4610
1!
12
b11100010 @
#4620
0!
02
#4630
1!
12
b11100011 @
#4640
0!
02
#4650
1!
12
b11100100 @
#4660
0!
02
#4670
1!
12
b11100101 @
#4680
0!
02
#4690
1!
12
b11100110 @
#4700
0!
02
#4710
1!
12
b11100111 @
#4720
0!
02
#4730
1!
12
b11101000 @
#4740
0!
02
#4750
1!
12
b11101001 @
#4760
0!
02
#4770
1!
12
b11101010 @
#4780
0!
02
#4790
1!
12
b11101011 @
#4800
0!
02
#4810
1!
12
b11101100 @
#4820
0!
02
#4830
1!
12
b11101101 @
#4840
0!
02
#4850
1!
12
b11101110 @
#4860
0!
02
#4870
1!
12
b11101111 @
#4880
0!
02
#4890
1!
12
b11110000 @
#4900
0!
02
#4910
1!
12
b11110001 @
#4920
0!
02
#4930
1!
12
b11110010 @
#4940
0!
02
#4950
1!
12
b11110011 @
#4960
0!
02
#4970
1!
12
b11110100 @
#4980
0!
02
#4990
1!
12
b11110101 @
#5000
0!
02
#5010
1!
12
b11110110 @
#5020
0!
02
#5030
1!
12
b11110111 @
#5040
0!
02
#5050
1!
12
b11111000 @
#5060
0!
02
#5070
1!
12
b11111001 @
#5080
0!
02
#5090
1!
12
1?
b11111010 @
#5100
0!
02
#5110
1!
12
0?
b11111011 @
#5120
0!
02
#5130
1!
12
b11111100 @
#5140
0!
02
#5150
1!
12
b11111101 @
#5160
0!
02
#5170
1!
12
b11111110 @
#5180
0!
02
#5190
1!
12
b11111111 @
#5200
0!
02
#5210
1!
12
b100000000 @
#5220
0!
02
#5230
1!
12
b100000001 @
#5240
0!
02
#5250
1!
12
b100000010 @
#5260
0!
02
#5270
1!
12
b100000011 @
#5280
0!
02
#5290
1!
12
b100000100 @
#5300
0!
02
#5310
1!
12
b100000101 @
#5320
0!
02
#5330
1!
12
b100000110 @
#5340
0!
02
#5350
1!
12
b100000111 @
#5360
0!
02
#5370
1!
12
b100001000 @
#5380
0!
02
#5390
1!
12
b100001001 @
#5400
0!
02
#5410
1!
12
b100001010 @
#5420
0!
02
#5430
1!
12
b100001011 @
#5440
0!
02
#5450
1!
12
b100001100 @
#5460
0!
02
#5470
1!
12
b100001101 @
#5480
0!
02
#5490
1!
12
b100001110 @
#5500
0!
02
#5510
1!
12
b100001111 @
#5520
0!
02
#5530
1!
12
b100010000 @
#5540
0!
02
#5550
1!
12
b100010001 @
#5560
0!
02
#5570
1!
12
b100010010 @
#5580
0!
02
#5590
1!
12
b100010011 @
#5600
0!
02
#5610
1!
12
b100010100 @
#5620
0!
02
#5630
1!
12
b100010101 @
#5640
0!
02
#5650
1!
12
b100010110 @
#5660
0!
02
#5670
1!
12
b100010111 @
#5680
0!
02
#5690
1!
12
b100011000 @
#5700
0!
02
#5710
1!
12
b100011001 @
#5720
0!
02
#5730
1!
12
b100011010 @
#5740
0!
02
#5750
1!
12
b100011011 @
#5760
0!
02
#5770
1!
12
b100011100 @
#5780
0!
02
#5790
1!
12
b100011101 @
#5800
0!
02
#5810
1!
12
b100011110 @
#5820
0!
02
#5830
1!
12
b100011111 @
#5840
0!
02
#5850
1!
12
b100100000 @
#5860
0!
02
#5870
1!
12
b100100001 @
#5880
0!
02
#5890
1!
12
b100100010 @
#5900
0!
02
#5910
1!
12
b100100011 @
#5920
0!
02
#5930
1!
12
b100100100 @
#5940
0!
02
#5950
1!
12
b100100101 @
#5960
0!
02
#5970
1!
12
b100100110 @
#5980
0!
02
#5990
1!
12
b100100111 @
#6000
0!
02
#6010
1!
12
b100101000 @
#6020
0!
02
#6030
1!
12
b100101001 @
#6040
0!
02
#6050
1!
12
b100101010 @
#6060
0!
02
#6070
1!
12
b100101011 @
#6080
0!
02
#6090
1!
12
b100101100 @
#6100
0!
02
#6110
1!
12
b100101101 @
#6120
0!
02
#6130
1!
12
b100101110 @
#6140
0!
02
#6150
1!
12
b100101111 @
#6160
0!
02
#6170
1!
12
b100110000 @
#6180
0!
02
#6190
1!
12
b100110001 @
#6200
0!
02
#6210
1!
12
b100110010 @
#6220
0!
02
#6230
1!
12
b100110011 @
#6240
0!
02
#6250
1!
12
b100110100 @
#6260
0!
02
#6270
1!
12
b100110101 @
#6280
0!
02
#6290
1!
12
b100110110 @
#6300
0!
02
#6310
1!
12
b100110111 @
#6320
0!
02
#6330
1!
12
b100111000 @
#6340
0!
02
#6350
1!
12
b100111001 @
#6360
0!
02
#6370
1!
12
b100111010 @
#6380
0!
02
#6390
1!
12
b100111011 @
#6400
0!
02
#6410
1!
12
b100111100 @
#6420
0!
02
#6430
1!
12
b100111101 @
#6440
0!
02
#6450
1!
12
b100111110 @
#6460
0!
02
#6470
1!
12
b100111111 @
#6480
0!
02
#6490
1!
12
b101000000 @
#6500
0!
02
#6510
1!
12
b101000001 @
#6520
0!
02
#6530
1!
12
b101000010 @
#6540
0!
02
#6550
1!
12
b101000011 @
#6560
0!
02
#6570
1!
12
b101000100 @
#6580
0!
02
#6590
1!
12
b101000101 @
#6600
0!
02
#6610
1!
12
b101000110 @
#6620
0!
02
#6630
1!
12
b101000111 @
#6640
0!
02
#6650
1!
12
b101001000 @
#6660
0!
02
#6670
1!
12
b101001001 @
#6680
0!
02
#6690
1!
12
b101001010 @
#6700
0!
02
#6710
1!
12
b101001011 @
#6720
0!
02
#6730
1!
12
b101001100 @
#6740
0!
02
#6750
1!
12
b101001101 @
#6760
0!
02
#6770
1!
12
b101001110 @
#6780
0!
02
#6790
1!
12
b101001111 @
#6800
0!
02
#6810
1!
12
b101010000 @
#6820
0!
02
#6830
1!
12
b101010001 @
#6840
0!
02
#6850
1!
12
b101010010 @
#6860
0!
02
#6870
1!
12
b101010011 @
#6880
0!
02
#6890
1!
12
b101010100 @
#6900
0!
02
#6910
1!
12
b101010101 @
#6920
0!
02
#6930
1!
12
b101010110 @
#6940
0!
02
#6950
1!
12
b101010111 @
#6960
0!
02
#6970
1!
12
b101011000 @
#6980
0!
02
#6990
1!
12
b101011001 @
#7000
0!
02
#7010
1!
12
b101011010 @
#7020
0!
02
#7030
1!
12
b101011011 @
#7040
0!
02
#7050
1!
12
b101011100 @
#7060
0!
02
#7070
1!
12
b101011101 @
#7080
0!
02
#7090
1!
12
b101011110 @
#7100
0!
02
#7110
1!
12
b101011111 @
#7120
0!
02
#7130
1!
12
b101100000 @
#7140
0!
02
#7150
1!
12
b101100001 @
#7160
0!
02
#7170
1!
12
b101100010 @
#7180
0!
02
#7190
1!
12
b101100011 @
#7200
0!
02
#7210
1!
12
b101100100 @
#7220
0!
02
#7230
1!
12
b101100101 @
#7240
0!
02
#7250
1!
12
b101100110 @
#7260
0!
02
#7270
1!
12
b101100111 @
#7280
0!
02
#7290
1!
12
b101101000 @
#7300
0!
02
#7310
1!
12
b101101001 @
#7320
0!
02
#7330
1!
12
b101101010 @
#7340
0!
02
#7350
1!
12
b101101011 @
#7360
0!
02
#7370
1!
12
b101101100 @
#7380
0!
02
#7390
1!
12
b101101101 @
#7400
0!
02
#7410
1!
12
b101101110 @
#7420
0!
02
#7430
1!
12
b101101111 @
#7440
0!
02
#7450
1!
12
b101110000 @
#7460
0!
02
#7470
1!
12
b101110001 @
#7480
0!
02
#7490
1!
12
b101110010 @
#7500
0!
02
#7510
1!
12
b101110011 @
#7520
0!
02
#7530
1!
12
b101110100 @
#7540
0!
02
#7550
1!
12
b101110101 @
#7560
0!
02
#7570
1!
12
b101110110 @
#7580
0!
02
#7590
1!
12
b101110111 @
#7600
0!
02
#7610
1!
12
b101111000 @
#7620
0!
02
#7630
1!
12
b101111001 @
#7640
0!
02
#7650
1!
12
b101111010 @
#7660
0!
02
#7670
1!
12
b101111011 @
#7680
0!
02
#7690
1!
12
b101111100 @
#7700
0!
02
#7710
1!
12
b101111101 @
#7720
0!
02
#7730
1!
12
b101111110 @
#7740
0!
02
#7750
1!
12
b101111111 @
#7760
0!
02
#7770
1!
12
b110000000 @
#7780
0!
02
#7790
1!
12
b110000001 @
#7800
0!
02
#7810
1!
12
b110000010 @
#7820
0!
02
#7830
1!
12
b110000011 @
#7840
0!
02
#7850
1!
12
b110000100 @
#7860
0!
02
#7870
1!
12
b110000101 @
#7880
0!
02
#7890
1!
12
b110000110 @
#7900
0!
02
#7910
1!
12
b110000111 @
#7920
0!
02
#7930
1!
12
b110001000 @
#7940
0!
02
#7950
1!
12
b110001001 @
#7960
0!
02
#7970
1!
12
b110001010 @
#7980
0!
02
#7990
1!
12
b110001011 @
#8000
0!
02
#8010
1!
12
b110001100 @
#8020
0!
02
#8030
1!
12
b110001101 @
#8040
0!
02
#8050
1!
12
b110001110 @
#8060
0!
02
#8070
1!
12
b110001111 @
#8080
0!
02
#8090
1!
12
b110010000 @
#8100
0!
02
#8110
1!
12
b110010001 @
#8120
0!
02
#8130
1!
12
b110010010 @
#8140
0!
02
#8150
1!
12
b110010011 @
#8160
0!
02
#8170
1!
12
b110010100 @
#8180
0!
02
#8190
1!
12
b110010101 @
#8200
0!
02
#8210
1!
12
b110010110 @
#8220
0!
02
#8230
1!
12
b110010111 @
#8240
0!
02
#8250
1!
12
b110011000 @
#8260
0!
02
#8270
1!
12
b110011001 @
#8280
0!
02
#8290
1!
12
b110011010 @
#8300
0!
02
#8310
1!
12
b110011011 @
#8320
0!
02
#8330
1!
12
b110011100 @
#8340
0!
02
#8350
1!
12
b110011101 @
#8360
0!
02
#8370
1!
12
b110011110 @
#8380
0!
02
#8390
1!
12
b110011111 @
#8400
0!
02
#8410
1!
12
b110100000 @
#8420
0!
02
#8430
1!
12
b110100001 @
#8440
0!
02
#8450
1!
12
b110100010 @
#8460
0!
02
#8470
1!
12
b110100011 @
#8480
0!
02
#8490
1!
12
b110100100 @
#8500
0!
02
#8510
1!
12
b110100101 @
#8520
0!
02
#8530
1!
12
b110100110 @
#8540
0!
02
#8550
1!
12
b110100111 @
#8560
0!
02
#8570
1!
12
b110101000 @
#8580
0!
02
#8590
1!
12
b110101001 @
#8600
0!
02
#8610
1!
12
b110101010 @
#8620
0!
02
#8630
1!
12
b110101011 @
#8640
0!
02
#8650
1!
12
b110101100 @
#8660
0!
02
#8670
1!
12
b110101101 @
#8680
0!
02
#8690
1!
12
b110101110 @
#8700
0!
02
#8710
1!
12
b110101111 @
#8720
0!
02
#8730
1!
12
b110110000 @
#8740
0!
02
#8750
1!
12
b110110001 @
#8760
0!
02
#8770
1!
12
b110110010 @
#8780
0!
02
#8790
1!
12
b110110011 @
#8800
0!
02
#8810
1!
12
b110110100 @
#8820
0!
02
#8830
1!
12
b110110101 @
#8840
0!
02
#8850
1!
12
b110110110 @
#8860
0!
02
#8870
1!
12
b110110111 @
#8880
0!
02
#8890
1!
12
b110111000 @
#8900
0!
02
#8910
1!
12
b110111001 @
#8920
0!
02
#8930
1!
12
b110111010 @
#8940
0!
02
#8950
1!
12
b110111011 @
#8960
0!
02
#8970
1!
12
b110111100 @
#8980
0!
02
#8990
1!
12
b110111101 @
#9000
0!
02
#9010
1!
12
b110111110 @
#9020
0!
02
#9030
1!
12
b110111111 @
#9040
0!
02
#9050
1!
12
b111000000 @
#9060
0!
02
#9070
1!
12
b111000001 @
#9080
0!
02
#9090
1!
12
b111000010 @
#9100
0!
02
#9110
1!
12
b111000011 @
#9120
0!
02
#9130
1!
12
b111000100 @
#9140
0!
02
#9150
1!
12
b111000101 @
#9160
0!
02
#9170
1!
12
b111000110 @
#9180
0!
02
#9190
1!
12
b111000111 @
#9200
0!
02
#9210
1!
12
b111001000 @
#9220
0!
02
#9230
1!
12
b111001001 @
#9240
0!
02
#9250
1!
12
b111001010 @
#9260
0!
02
#9270
1!
12
b111001011 @
#9280
0!
02
#9290
1!
12
b111001100 @
#9300
0!
02
#9310
1!
12
b111001101 @
#9320
0!
02
#9330
1!
12
b111001110 @
#9340
0!
02
#9350
1!
12
b111001111 @
#9360
0!
02
#9370
1!
12
b111010000 @
#9380
0!
02
#9390
1!
12
b111010001 @
#9400
0!
02
#9410
1!
12
b111010010 @
#9420
0!
02
#9430
1!
12
b111010011 @
#9440
0!
02
#9450
1!
12
b111010100 @
#9460
0!
02
#9470
1!
12
b111010101 @
#9480
0!
02
#9490
1!
12
b111010110 @
